chromapalette/__init__.py
chromapalette/chrome_palette/__init__.py
chroma_palette-1.0.4.dist-info/LICENSE
chroma_palette-1.0.4.dist-info/METADATA
chroma_palette-1.0.4.dist-info/WHEEL
chroma_palette-1.0.4.dist-info/top_level.txt
chroma_palette-1.0.4.dist-info/RECORD
