Metadata-Version: 2.1
Name: chroma_palette
Version: 1.0.4
Summary: Chroma Palette - Text Styling Library
Author: Vinay Kumar (vk_billava)
Author-email: <vinaykumarbillava@gmail.com>
Keywords: python,terminal,color,palette,color palette,termina palette,terminal,chroma,chroma palette
Classifier: Development Status :: 4 - Beta
Classifier: Intended Audience :: Developers
Classifier: Programming Language :: Python :: 3
Classifier: Operating System :: Unix
Classifier: Operating System :: MacOS :: MacOS X
Classifier: Operating System :: Microsoft :: Windows
License-File: LICENSE
